fluxengine/__init__.py
fluxengine/configs/example_config.conf
fluxengine/configs/socatv4_sst_salinity_gradients-N00.conf
fluxengine/configs/takahashi09_verification.conf
fluxengine/configs/example_case_studies/readme.txt
fluxengine/configs/example_case_studies/CS1_in_situ_cruise_data/insitu_case_study_bulk_H06.conf
fluxengine/configs/example_case_studies/CS1_in_situ_cruise_data/insitu_case_study_bulk_H06_reanalysed.conf
fluxengine/configs/example_case_studies/CS2_fixed_station_data/fixed_station.conf
fluxengine/configs/example_case_studies/CS2_fixed_station_data/fixed_station_reanalysed.conf
fluxengine/configs/example_case_studies/CS3_surfactant_suppression_of_N2O/N2O_rapid_N00.conf
fluxengine/configs/example_case_studies/CS3_surfactant_suppression_of_N2O/N2O_rapid_N00_surfactant.conf
fluxengine/configs/example_case_studies/CS4_turbulence_k_parameterisation/run_Zappa2007_20cm.conf
fluxengine/configs/example_case_studies/CS4_turbulence_k_parameterisation/run_wanninkhof2014.conf
fluxengine/core/__init__.py
fluxengine/core/data_preprocessing.py
fluxengine/core/datalayer.py
fluxengine/core/debug_tools.py
fluxengine/core/fe_core.py
fluxengine/core/fe_setup_tools.py
fluxengine/core/process_indicator_layers.py
fluxengine/core/rate_parameterisation.py
fluxengine/core/settings.py
fluxengine/core/settings.xml
fluxengine/data/Longhurst-provinces-mask.nc
fluxengine/data/Oceans-combined-final-complete.nc
fluxengine/data/World_Seas-IHO-mask.nc
fluxengine/data/World_Seas-final-complete_IGA.nc
fluxengine/data/onedeg_land.nc
fluxengine/data/verification_data/SOCATv4/20100101_OCF-CO2-GLO-1M-KRG-CLIM.nc
fluxengine/data/verification_data/SOCATv4/20100201_OCF-CO2-GLO-1M-KRG-CLIM.nc
fluxengine/data/verification_data/SOCATv4/20100301_OCF-CO2-GLO-1M-KRG-CLIM.nc
fluxengine/data/verification_data/SOCATv4/20100401_OCF-CO2-GLO-1M-KRG-CLIM.nc
fluxengine/data/verification_data/SOCATv4/20100501_OCF-CO2-GLO-1M-KRG-CLIM.nc
fluxengine-4.0.9.1.dist-info/LICENSE
fluxengine-4.0.9.1.dist-info/METADATA
fluxengine-4.0.9.1.dist-info/WHEEL
fluxengine-4.0.9.1.dist-info/top_level.txt
fluxengine-4.0.9.1.dist-info/RECORD
