Metadata-Version: 2.1
Name: fluxengine
Version: 4.0.9.1
Summary: Open-source toolkit for calculating atmosphere-ocean gas transfer
Home-page: https://github.com/oceanflux-ghg/FluxEngine
Author: Tom Holding and Jamie Shutler
Author-email: j.d.shutler@exeter.ac.uk, t.m.holding@exeter.ac.uk
License: Creative Commons Attribution-Noncommercial-Share Alike license
Project-URL: Source Code, https://github.com/oceanflux-ghg/FluxEngine
Project-URL: Ancillary Tools, https://github.com/oceanflux-ghg/FluxEngineAncillaryTools
Project-URL: More Info, http://www.oceanflux-ghg.org/Products/FluxEngine
License-File: LICENSE
Requires-Dist: numpy >=1.20.0
Requires-Dist: pandas >=0.24.2
Requires-Dist: matplotlib >=3.1.0
Requires-Dist: netCDF4 >=1.4.2
Requires-Dist: argparse >=1.1
Requires-Dist: scipy >=1.3.0
Requires-Dist: jupyter >=1.0.0
